{
"meta":{"test_sets":[],"test_metrics":[],"learn_metrics":[{"best_value":"Min","name":"Logloss"}],"launch_mode":"Train","parameters":"","iteration_count":300,"learn_sets":["learn"],"name":"experiment"},
"iterations":[
{"learn":[0.6820371411],"iteration":0,"passed_time":0.1635451565,"remaining_time":48.9000018},
{"learn":[0.6733078679],"iteration":1,"passed_time":0.1963159669,"remaining_time":29.25107907},
{"learn":[0.6661790106],"iteration":2,"passed_time":0.2325638135,"remaining_time":23.02381754},
{"learn":[0.659941233],"iteration":3,"passed_time":0.2720688661,"remaining_time":20.13309609},
{"learn":[0.6543358928],"iteration":4,"passed_time":0.3105270077,"remaining_time":18.32109345},
{"learn":[0.6507608689],"iteration":5,"passed_time":0.3512787441,"remaining_time":17.21265846},
{"learn":[0.6464585003],"iteration":6,"passed_time":0.3915926362,"remaining_time":16.39094891},
{"learn":[0.6425283527],"iteration":7,"passed_time":0.4354659041,"remaining_time":15.8945055},
{"learn":[0.639361976],"iteration":8,"passed_time":0.4734374205,"remaining_time":15.30780993},
{"learn":[0.636512975],"iteration":9,"passed_time":0.5099253445,"remaining_time":14.78783499},
{"learn":[0.6339665616],"iteration":10,"passed_time":0.5466990887,"remaining_time":14.36327606},
{"learn":[0.6316388236],"iteration":11,"passed_time":0.5840162228,"remaining_time":14.01638935},
{"learn":[0.6295472955],"iteration":12,"passed_time":0.6243914147,"remaining_time":13.78464123},
{"learn":[0.6276556956],"iteration":13,"passed_time":0.6655546917,"remaining_time":13.59633156},
{"learn":[0.6261511266],"iteration":14,"passed_time":0.7072800953,"remaining_time":13.43832181},
{"learn":[0.6246120096],"iteration":15,"passed_time":0.747326794,"remaining_time":13.26505059},
{"learn":[0.6233120595],"iteration":16,"passed_time":0.7849193089,"remaining_time":13.06659791},
{"learn":[0.6218663866],"iteration":17,"passed_time":0.8249310365,"remaining_time":12.92391957},
{"learn":[0.6206124411],"iteration":18,"passed_time":0.8733575165,"remaining_time":12.91649801},
{"learn":[0.6194095947],"iteration":19,"passed_time":0.9126006034,"remaining_time":12.77640845},
{"learn":[0.618386471],"iteration":20,"passed_time":0.9500002239,"remaining_time":12.62143155},
{"learn":[0.6173096173],"iteration":21,"passed_time":0.9869757559,"remaining_time":12.47178455},
{"learn":[0.6163931167],"iteration":22,"passed_time":1.021520311,"remaining_time":12.30265766},
{"learn":[0.615374656],"iteration":23,"passed_time":1.061263463,"remaining_time":12.20452983},
{"learn":[0.6145951835],"iteration":24,"passed_time":1.100418461,"remaining_time":12.10460307},
{"learn":[0.6135140191],"iteration":25,"passed_time":1.13575424,"remaining_time":11.96910237},
{"learn":[0.6128065642],"iteration":26,"passed_time":1.170589006,"remaining_time":11.83595551},
{"learn":[0.6120903742],"iteration":27,"passed_time":1.206825276,"remaining_time":11.72344554},
{"learn":[0.6113174337],"iteration":28,"passed_time":1.244733209,"remaining_time":11.63181723},
{"learn":[0.6106985263],"iteration":29,"passed_time":1.284171167,"remaining_time":11.5575405},
{"learn":[0.6102280104],"iteration":30,"passed_time":1.326803365,"remaining_time":11.5132292},
{"learn":[0.6097567904],"iteration":31,"passed_time":1.365517489,"remaining_time":11.43620897},
{"learn":[0.6091400685],"iteration":32,"passed_time":1.401225656,"remaining_time":11.3371894},
{"learn":[0.6085689677],"iteration":33,"passed_time":1.435642754,"remaining_time":11.23179331},
{"learn":[0.6080196742],"iteration":34,"passed_time":1.468724136,"remaining_time":11.12033989},
{"learn":[0.6074477103],"iteration":35,"passed_time":1.506071395,"remaining_time":11.04452356},
{"learn":[0.607063605],"iteration":36,"passed_time":1.550627337,"remaining_time":11.02202674},
{"learn":[0.6065784184],"iteration":37,"passed_time":1.587798446,"remaining_time":10.94745244},
{"learn":[0.6059887171],"iteration":38,"passed_time":1.621651378,"remaining_time":10.85258999},
{"learn":[0.6056616734],"iteration":39,"passed_time":1.655981688,"remaining_time":10.76388097},
{"learn":[0.6052578954],"iteration":40,"passed_time":1.695538622,"remaining_time":10.71084154},
{"learn":[0.6048580509],"iteration":41,"passed_time":1.733155587,"remaining_time":10.64652718},
{"learn":[0.604416468],"iteration":42,"passed_time":1.780577405,"remaining_time":10.64205565},
{"learn":[0.6041056369],"iteration":43,"passed_time":1.815940589,"remaining_time":10.56547252},
{"learn":[0.6038119808],"iteration":44,"passed_time":1.851519646,"remaining_time":10.49194466},
{"learn":[0.6035046028],"iteration":45,"passed_time":1.886031138,"remaining_time":10.41417194},
{"learn":[0.6031574606],"iteration":46,"passed_time":1.926760082,"remaining_time":10.37170852},
{"learn":[0.6027767882],"iteration":47,"passed_time":1.968577695,"remaining_time":10.3350329},
{"learn":[0.6024868653],"iteration":48,"passed_time":2.012768645,"remaining_time":10.31030469},
{"learn":[0.6020062944],"iteration":49,"passed_time":2.05296546,"remaining_time":10.2648273},
{"learn":[0.6017767083],"iteration":50,"passed_time":2.088407986,"remaining_time":10.19634487},
{"learn":[0.6013113354],"iteration":51,"passed_time":2.128800218,"remaining_time":10.1527395},
{"learn":[0.6009974345],"iteration":52,"passed_time":2.170119859,"remaining_time":10.11357746},
{"learn":[0.6007252526],"iteration":53,"passed_time":2.211585561,"remaining_time":10.07500089},
{"learn":[0.6004582681],"iteration":54,"passed_time":2.248238648,"remaining_time":10.01488125},
{"learn":[0.6001609188],"iteration":55,"passed_time":2.288944222,"remaining_time":9.973256965},
{"learn":[0.5997669148],"iteration":56,"passed_time":2.334145603,"remaining_time":9.950831255},
{"learn":[0.5995660636],"iteration":57,"passed_time":2.368169347,"remaining_time":9.88098245},
{"learn":[0.5993818202],"iteration":58,"passed_time":2.40814765,"remaining_time":9.836670907},
{"learn":[0.5991638451],"iteration":59,"passed_time":2.445069227,"remaining_time":9.78027691},
{"learn":[0.5988526797],"iteration":60,"passed_time":2.485156291,"remaining_time":9.736923829},
{"learn":[0.5986710838],"iteration":61,"passed_time":2.521922033,"remaining_time":9.680926515},
{"learn":[0.5985077036],"iteration":62,"passed_time":2.559684137,"remaining_time":9.629287944},
{"learn":[0.5983577815],"iteration":63,"passed_time":2.597325604,"remaining_time":9.577638164},
{"learn":[0.5981833405],"iteration":64,"passed_time":2.63492973,"remaining_time":9.526284408},
{"learn":[0.5980151598],"iteration":65,"passed_time":2.671992509,"remaining_time":9.473427987},
{"learn":[0.5977385464],"iteration":66,"passed_time":2.717835455,"remaining_time":9.451577031},
{"learn":[0.5975572548],"iteration":67,"passed_time":2.757137218,"remaining_time":9.406703451},
{"learn":[0.597379109],"iteration":68,"passed_time":2.793028865,"remaining_time":9.350574897},
{"learn":[0.5972265124],"iteration":69,"passed_time":2.829736122,"remaining_time":9.2977044},
{"learn":[0.597083005],"iteration":70,"passed_time":2.86434134,"remaining_time":9.238509393},
{"learn":[0.5969520986],"iteration":71,"passed_time":2.900492094,"remaining_time":9.184891632},
{"learn":[0.5968225489],"iteration":72,"passed_time":2.943303005,"remaining_time":9.152462768},
{"learn":[0.5966110042],"iteration":73,"passed_time":2.98286834,"remaining_time":9.109841147},
{"learn":[0.5964295736],"iteration":74,"passed_time":3.022951513,"remaining_time":9.068854539},
{"learn":[0.5963293877],"iteration":75,"passed_time":3.058386498,"remaining_time":9.014191784},
{"learn":[0.5962195766],"iteration":76,"passed_time":3.096981416,"remaining_time":8.969179944},
{"learn":[0.5961019462],"iteration":77,"passed_time":3.134540756,"remaining_time":8.921385228},
{"learn":[0.595975044],"iteration":78,"passed_time":3.185640223,"remaining_time":8.911727713},
{"learn":[0.5958425136],"iteration":79,"passed_time":3.223085329,"remaining_time":8.863484656},
{"learn":[0.5956527617],"iteration":80,"passed_time":3.265112688,"remaining_time":8.827897267},
{"learn":[0.5955848993],"iteration":81,"passed_time":3.303453117,"remaining_time":8.78235097},
{"learn":[0.5954893681],"iteration":82,"passed_time":3.338113527,"remaining_time":8.727357053},
{"learn":[0.5953375706],"iteration":83,"passed_time":3.380921203,"remaining_time":8.69379738},
{"learn":[0.595248039],"iteration":84,"passed_time":3.419560756,"remaining_time":8.649477207},
{"learn":[0.5951464512],"iteration":85,"passed_time":3.456910824,"remaining_time":8.602080423},
{"learn":[0.5950218093],"iteration":86,"passed_time":3.494665232,"remaining_time":8.555904533},
{"learn":[0.5949526308],"iteration":87,"passed_time":3.526039463,"remaining_time":8.494549615},
{"learn":[0.5948666744],"iteration":88,"passed_time":3.560586222,"remaining_time":8.441389807},
{"learn":[0.5946724503],"iteration":89,"passed_time":3.602054762,"remaining_time":8.404794446},
{"learn":[0.5946222685],"iteration":90,"passed_time":3.640867757,"remaining_time":8.36199298},
{"learn":[0.5942648137],"iteration":91,"passed_time":3.682094682,"remaining_time":8.324735802},
{"learn":[0.5941281812],"iteration":92,"passed_time":3.719027074,"remaining_time":8.277834454},
{"learn":[0.5940057941],"iteration":93,"passed_time":3.753888641,"remaining_time":8.226607022},
{"learn":[0.5939405933],"iteration":94,"passed_time":3.790470128,"remaining_time":8.17943554},
{"learn":[0.5937869776],"iteration":95,"passed_time":3.829641178,"remaining_time":8.137987503},
{"learn":[0.593683493],"iteration":96,"passed_time":3.866169612,"remaining_time":8.091055992},
{"learn":[0.5935913845],"iteration":97,"passed_time":3.906758058,"remaining_time":8.052705385},
{"learn":[0.5934148746],"iteration":98,"passed_time":3.943678662,"remaining_time":8.006862738},
{"learn":[0.5933366148],"iteration":99,"passed_time":3.978951004,"remaining_time":7.957902009},
{"learn":[0.5932593078],"iteration":100,"passed_time":4.01476727,"remaining_time":7.910284027},
{"learn":[0.5931196307],"iteration":101,"passed_time":4.058702634,"remaining_time":7.878658053},
{"learn":[0.5930379633],"iteration":102,"passed_time":4.098796097,"remaining_time":7.839444962},
{"learn":[0.5929720055],"iteration":103,"passed_time":4.135215942,"remaining_time":7.793291582},
{"learn":[0.5928687377],"iteration":104,"passed_time":4.173263855,"remaining_time":7.750347159},
{"learn":[0.5928015165],"iteration":105,"passed_time":4.20894009,"remaining_time":7.703154505},
{"learn":[0.5926999736],"iteration":106,"passed_time":4.243795973,"remaining_time":7.65469741},
{"learn":[0.5926062021],"iteration":107,"passed_time":4.278509717,"remaining_time":7.606239497},
{"learn":[0.5925156921],"iteration":108,"passed_time":4.319046898,"remaining_time":7.568238142},
{"learn":[0.5924426832],"iteration":109,"passed_time":4.356125741,"remaining_time":7.524217189},
{"learn":[0.5923586354],"iteration":110,"passed_time":4.390392121,"remaining_time":7.475532531},
{"learn":[0.5923018077],"iteration":111,"passed_time":4.42887762,"remaining_time":7.434187433},
{"learn":[0.5922614491],"iteration":112,"passed_time":4.463925756,"remaining_time":7.387204569},
{"learn":[0.5922034626],"iteration":113,"passed_time":4.499698017,"remaining_time":7.341612555},
{"learn":[0.5921128141],"iteration":114,"passed_time":4.541580661,"remaining_time":7.306021063},
{"learn":[0.5920376454],"iteration":115,"passed_time":4.575700211,"remaining_time":7.258007231},
{"learn":[0.5919333886],"iteration":116,"passed_time":4.610240046,"remaining_time":7.210888276},
{"learn":[0.5917663374],"iteration":117,"passed_time":4.648535568,"remaining_time":7.169775198},
{"learn":[0.5916700339],"iteration":118,"passed_time":4.684182915,"remaining_time":7.124681577},
{"learn":[0.5915525378],"iteration":119,"passed_time":4.72035168,"remaining_time":7.08052752},
{"learn":[0.5914852612],"iteration":120,"passed_time":4.761403117,"remaining_time":7.043728578},
{"learn":[0.5913913852],"iteration":121,"passed_time":4.801085611,"remaining_time":7.004862612},
{"learn":[0.5912784333],"iteration":122,"passed_time":4.83916115,"remaining_time":6.963670924},
{"learn":[0.5909785993],"iteration":123,"passed_time":4.883053806,"remaining_time":6.930786048},
{"learn":[0.5908787113],"iteration":124,"passed_time":4.920861922,"remaining_time":6.889206691},
{"learn":[0.5907985971],"iteration":125,"passed_time":4.957941847,"remaining_time":6.846681599},
{"learn":[0.5907245907],"iteration":126,"passed_time":4.995171543,"remaining_time":6.804446274},
{"learn":[0.590652374],"iteration":127,"passed_time":5.03180195,"remaining_time":6.761483871},
{"learn":[0.590404057],"iteration":128,"passed_time":5.073988763,"remaining_time":6.725985105},
{"learn":[0.5902918497],"iteration":129,"passed_time":5.108468042,"remaining_time":6.680304363},
{"learn":[0.5902136243],"iteration":130,"passed_time":5.141741227,"remaining_time":6.633238683},
{"learn":[0.5900230861],"iteration":131,"passed_time":5.185489071,"remaining_time":6.599713363},
{"learn":[0.5899233318],"iteration":132,"passed_time":5.219090309,"remaining_time":6.553293846},
{"learn":[0.5898056288],"iteration":133,"passed_time":5.256148711,"remaining_time":6.511348404},
{"learn":[0.5897242692],"iteration":134,"passed_time":5.294066083,"remaining_time":6.470525212},
{"learn":[0.5896191544],"iteration":135,"passed_time":5.327548371,"remaining_time":6.424396565},
{"learn":[0.5895302612],"iteration":136,"passed_time":5.365546281,"remaining_time":6.383825137},
{"learn":[0.5893514359],"iteration":137,"passed_time":5.408162549,"remaining_time":6.348712558},
{"learn":[0.5891929191],"iteration":138,"passed_time":5.459863902,"remaining_time":6.324015024},
{"learn":[0.5890760592],"iteration":139,"passed_time":5.508180481,"remaining_time":6.295063406},
{"learn":[0.5889901927],"iteration":140,"passed_time":5.557478579,"remaining_time":6.266943929},
{"learn":[0.5888889405],"iteration":141,"passed_time":5.602863621,"remaining_time":6.234172198},
{"learn":[0.5888244416],"iteration":142,"passed_time":5.645211214,"remaining_time":6.197889235},
{"learn":[0.5887492408],"iteration":143,"passed_time":5.692864548,"remaining_time":6.167269926},
{"learn":[0.5886275088],"iteration":144,"passed_time":5.737601731,"remaining_time":6.133298402},
{"learn":[0.5885481505],"iteration":145,"passed_time":5.77848165,"remaining_time":6.095110781},
{"learn":[0.588467204],"iteration":146,"passed_time":5.815375147,"remaining_time":6.052737398},
{"learn":[0.5883706215],"iteration":147,"passed_time":5.856525389,"remaining_time":6.014809859},
{"learn":[0.5882665416],"iteration":148,"passed_time":5.899702412,"remaining_time":5.978893049},
{"learn":[0.5881863823],"iteration":149,"passed_time":5.944859529,"remaining_time":5.944859529},
{"learn":[0.5881072668],"iteration":150,"passed_time":5.984345497,"remaining_time":5.905082643},
{"learn":[0.5880089838],"iteration":151,"passed_time":6.022443009,"remaining_time":5.863957666},
{"learn":[0.5879179769],"iteration":152,"passed_time":6.059256982,"remaining_time":5.821639062},
{"learn":[0.5878388763],"iteration":153,"passed_time":6.0987139,"remaining_time":5.781897594},
{"learn":[0.5877315019],"iteration":154,"passed_time":6.147700529,"remaining_time":5.751074689},
{"learn":[0.5876513593],"iteration":155,"passed_time":6.189028834,"remaining_time":5.712949693},
{"learn":[0.5875545228],"iteration":156,"passed_time":6.23873343,"remaining_time":5.682413251},
{"learn":[0.5874851907],"iteration":157,"passed_time":6.278557114,"remaining_time":5.642753862},
{"learn":[0.5873984343],"iteration":158,"passed_time":6.318205984,"remaining_time":5.602937382},
{"learn":[0.5873224436],"iteration":159,"passed_time":6.361284313,"remaining_time":5.566123774},
{"learn":[0.5872031884],"iteration":160,"passed_time":6.40396076,"remaining_time":5.528885377},
{"learn":[0.5871241836],"iteration":161,"passed_time":6.441000921,"remaining_time":5.486778562},
{"learn":[0.5870060482],"iteration":162,"passed_time":6.476697111,"remaining_time":5.44360432},
{"learn":[0.5869449037],"iteration":163,"passed_time":6.514705697,"remaining_time":5.402438871},
{"learn":[0.5868175279],"iteration":164,"passed_time":6.551347762,"remaining_time":5.360193623},
{"learn":[0.5867320216],"iteration":165,"passed_time":6.59083257,"remaining_time":5.320310629},
{"learn":[0.5866509166],"iteration":166,"passed_time":6.631447345,"remaining_time":5.281332317},
{"learn":[0.5865884449],"iteration":167,"passed_time":6.666453494,"remaining_time":5.237927745},
{"learn":[0.5865264152],"iteration":168,"passed_time":6.702574693,"remaining_time":5.195486893},
{"learn":[0.5864680373],"iteration":169,"passed_time":6.745423364,"remaining_time":5.158264926},
{"learn":[0.5863195091],"iteration":170,"passed_time":6.791986178,"remaining_time":5.123779047},
{"learn":[0.5862572459],"iteration":171,"passed_time":6.831468016,"remaining_time":5.083883175},
{"learn":[0.5861991231],"iteration":172,"passed_time":6.866834601,"remaining_time":5.040971066},
{"learn":[0.586111899],"iteration":173,"passed_time":6.911167355,"remaining_time":5.004638429},
{"learn":[0.5860306137],"iteration":174,"passed_time":6.954000773,"remaining_time":4.967143409},
{"learn":[0.5859687179],"iteration":175,"passed_time":6.986336249,"remaining_time":4.922191448},
{"learn":[0.5858981668],"iteration":176,"passed_time":7.022253938,"remaining_time":4.879871381},
{"learn":[0.5858368812],"iteration":177,"passed_time":7.057734827,"remaining_time":4.83732387},
{"learn":[0.5857646407],"iteration":178,"passed_time":7.094525566,"remaining_time":4.795740746},
{"learn":[0.5856944543],"iteration":179,"passed_time":7.131841608,"remaining_time":4.754561072},
{"learn":[0.585622126],"iteration":180,"passed_time":7.172518565,"remaining_time":4.715633752},
{"learn":[0.5855394197],"iteration":181,"passed_time":7.206549439,"remaining_time":4.672378208},
{"learn":[0.5854593855],"iteration":182,"passed_time":7.245691107,"remaining_time":4.632491036},
{"learn":[0.5853824336],"iteration":183,"passed_time":7.284754525,"remaining_time":4.592562635},
{"learn":[0.5853317428],"iteration":184,"passed_time":7.319849359,"remaining_time":4.550176629},
{"learn":[0.5852669354],"iteration":185,"passed_time":7.357638808,"remaining_time":4.50952056},
{"learn":[0.5852080445],"iteration":186,"passed_time":7.395047086,"remaining_time":4.468664817},
{"learn":[0.5851267345],"iteration":187,"passed_time":7.430932414,"remaining_time":4.426938459},
{"learn":[0.5850616051],"iteration":188,"passed_time":7.471909982,"remaining_time":4.388264592},
{"learn":[0.5850029533],"iteration":189,"passed_time":7.512192902,"remaining_time":4.349164312},
{"learn":[0.5849406025],"iteration":190,"passed_time":7.550559997,"remaining_time":4.308958323},
{"learn":[0.5848803113],"iteration":191,"passed_time":7.590768173,"remaining_time":4.269807097},
{"learn":[0.5847886552],"iteration":192,"passed_time":7.624530808,"remaining_time":4.227071484},
{"learn":[0.5847229765],"iteration":193,"passed_time":7.665372927,"remaining_time":4.188296548},
{"learn":[0.5846628397],"iteration":194,"passed_time":7.70471499,"remaining_time":4.148692687},
{"learn":[0.5846009385],"iteration":195,"passed_time":7.740277847,"remaining_time":4.107086205},
{"learn":[0.584515551],"iteration":196,"passed_time":7.782971306,"remaining_time":4.069269261},
{"learn":[0.5844533436],"iteration":197,"passed_time":7.822645166,"remaining_time":4.02984751},
{"learn":[0.5843743147],"iteration":198,"passed_time":7.858249294,"remaining_time":3.988357682},
{"learn":[0.5843091737],"iteration":199,"passed_time":7.894955405,"remaining_time":3.947477702},
{"learn":[0.5841913445],"iteration":200,"passed_time":7.939976852,"remaining_time":3.910734867},
{"learn":[0.5841254363],"iteration":201,"passed_time":7.975385288,"remaining_time":3.869246328},
{"learn":[0.5840742665],"iteration":202,"passed_time":8.00936988,"remaining_time":3.827137332},
{"learn":[0.584027348],"iteration":203,"passed_time":8.046043446,"remaining_time":3.786373387},
{"learn":[0.5839714393],"iteration":204,"passed_time":8.085520257,"remaining_time":3.746948412},
{"learn":[0.5839111277],"iteration":205,"passed_time":8.122538706,"remaining_time":3.706401157},
{"learn":[0.5838448633],"iteration":206,"passed_time":8.160749986,"remaining_time":3.666423907},
{"learn":[0.5837955273],"iteration":207,"passed_time":8.200411073,"remaining_time":3.627104898},
{"learn":[0.5837407733],"iteration":208,"passed_time":8.235287055,"remaining_time":3.585699149},
{"learn":[0.5836767958],"iteration":209,"passed_time":8.273645095,"remaining_time":3.545847898},
{"learn":[0.5836051244],"iteration":210,"passed_time":8.313402449,"remaining_time":3.506601033},
{"learn":[0.5835335748],"iteration":211,"passed_time":8.353805787,"remaining_time":3.467617497},
{"learn":[0.5834700462],"iteration":212,"passed_time":8.391923353,"remaining_time":3.427687003},
{"learn":[0.5833583598],"iteration":213,"passed_time":8.429297475,"remaining_time":3.387474686},
{"learn":[0.5832759756],"iteration":214,"passed_time":8.473490012,"remaining_time":3.349984424},
{"learn":[0.5832159745],"iteration":215,"passed_time":8.523838541,"remaining_time":3.314826099},
{"learn":[0.5831742319],"iteration":216,"passed_time":8.57148561,"remaining_time":3.278494496},
{"learn":[0.5831280291],"iteration":217,"passed_time":8.620004963,"remaining_time":3.242387188},
{"learn":[0.5830760979],"iteration":218,"passed_time":8.66508036,"remaining_time":3.204892736},
{"learn":[0.5830213651],"iteration":219,"passed_time":8.707664471,"remaining_time":3.166423444},
{"learn":[0.5829691349],"iteration":220,"passed_time":8.753525062,"remaining_time":3.129088144},
{"learn":[0.5828789588],"iteration":221,"passed_time":8.795675346,"remaining_time":3.090372419},
{"learn":[0.5827787042],"iteration":222,"passed_time":8.846890684,"remaining_time":3.054755976},
{"learn":[0.5827112709],"iteration":223,"passed_time":8.89578673,"remaining_time":3.018213355},
{"learn":[0.5826553409],"iteration":224,"passed_time":8.940088268,"remaining_time":2.980029423},
{"learn":[0.5826058655],"iteration":225,"passed_time":8.983580591,"remaining_time":2.941526388},
{"learn":[0.5825471958],"iteration":226,"passed_time":9.025754799,"remaining_time":2.902555508},
{"learn":[0.5824538923],"iteration":227,"passed_time":9.073434987,"remaining_time":2.865295259},
{"learn":[0.5823901555],"iteration":228,"passed_time":9.118379351,"remaining_time":2.827095781},
{"learn":[0.5823432573],"iteration":229,"passed_time":9.161736854,"remaining_time":2.788354695},
{"learn":[0.5822947936],"iteration":230,"passed_time":9.206316888,"remaining_time":2.749938811},
{"learn":[0.5822382269],"iteration":231,"passed_time":9.256215584,"remaining_time":2.713028706},
{"learn":[0.5821735383],"iteration":232,"passed_time":9.307962249,"remaining_time":2.676538501},
{"learn":[0.582088229],"iteration":233,"passed_time":9.372303515,"remaining_time":2.643470222},
{"learn":[0.5820075247],"iteration":234,"passed_time":9.427461022,"remaining_time":2.607595602},
{"learn":[0.5819282518],"iteration":235,"passed_time":9.482385757,"remaining_time":2.571494443},
{"learn":[0.5818257362],"iteration":236,"passed_time":9.532933364,"remaining_time":2.534070894},
{"learn":[0.5817616878],"iteration":237,"passed_time":9.576103727,"remaining_time":2.494615257},
{"learn":[0.5816857032],"iteration":238,"passed_time":9.621450342,"remaining_time":2.455683979},
{"learn":[0.5816376281],"iteration":239,"passed_time":9.660479498,"remaining_time":2.415119875},
{"learn":[0.5815846196],"iteration":240,"passed_time":9.695129305,"remaining_time":2.373496386},
{"learn":[0.5815202574],"iteration":241,"passed_time":9.734636855,"remaining_time":2.333094783},
{"learn":[0.5814578192],"iteration":242,"passed_time":9.773187574,"remaining_time":2.292476098},
{"learn":[0.5814057842],"iteration":243,"passed_time":9.81011225,"remaining_time":2.251501172},
{"learn":[0.58135595],"iteration":244,"passed_time":9.849311538,"remaining_time":2.211069937},
{"learn":[0.5813144609],"iteration":245,"passed_time":9.889238756,"remaining_time":2.170808507},
{"learn":[0.5812295558],"iteration":246,"passed_time":9.934749131,"remaining_time":2.131747789},
{"learn":[0.5811694357],"iteration":247,"passed_time":9.982304335,"remaining_time":2.093063812},
{"learn":[0.5811111058],"iteration":248,"passed_time":10.02549754,"remaining_time":2.053415158},
{"learn":[0.5810389191],"iteration":249,"passed_time":10.06796101,"remaining_time":2.013592203},
{"learn":[0.5809888206],"iteration":250,"passed_time":10.11006381,"remaining_time":1.973677795},
{"learn":[0.5809122107],"iteration":251,"passed_time":10.15663715,"remaining_time":1.934597552},
{"learn":[0.5808487427],"iteration":252,"passed_time":10.20907159,"remaining_time":1.896546896},
{"learn":[0.5807768465],"iteration":253,"passed_time":10.25289642,"remaining_time":1.856823761},
{"learn":[0.5807240514],"iteration":254,"passed_time":10.29329371,"remaining_time":1.816463596},
{"learn":[0.5806409096],"iteration":255,"passed_time":10.33798085,"remaining_time":1.776840459},
{"learn":[0.5805923457],"iteration":256,"passed_time":10.3792493,"remaining_time":1.736605914},
{"learn":[0.58053797],"iteration":257,"passed_time":10.424038,"remaining_time":1.696936419},
{"learn":[0.5804589706],"iteration":258,"passed_time":10.47036511,"remaining_time":1.657470925},
{"learn":[0.5804006176],"iteration":259,"passed_time":10.5107645,"remaining_time":1.617040693},
{"learn":[0.5803279048],"iteration":260,"passed_time":10.54934829,"remaining_time":1.576339399},
{"learn":[0.5802718407],"iteration":261,"passed_time":10.58948577,"remaining_time":1.535879615},
{"learn":[0.5802210708],"iteration":262,"passed_time":10.62964986,"remaining_time":1.495426025},
{"learn":[0.580132791],"iteration":263,"passed_time":10.66999733,"remaining_time":1.454999636},
{"learn":[0.5800857738],"iteration":264,"passed_time":10.70751457,"remaining_time":1.414200038},
{"learn":[0.5800428984],"iteration":265,"passed_time":10.74563189,"remaining_time":1.37350182},
{"learn":[0.5800014917],"iteration":266,"passed_time":10.79088829,"remaining_time":1.333705294},
{"learn":[0.5799582308],"iteration":267,"passed_time":10.83197571,"remaining_time":1.293370235},
{"learn":[0.5799279875],"iteration":268,"passed_time":10.87360957,"remaining_time":1.253092552},
{"learn":[0.5798676829],"iteration":269,"passed_time":10.91581995,"remaining_time":1.212868883},
{"learn":[0.5798116916],"iteration":270,"passed_time":10.95834889,"remaining_time":1.172664642},
{"learn":[0.5797168105],"iteration":271,"passed_time":10.99971656,"remaining_time":1.132323763},
{"learn":[0.5796633916],"iteration":272,"passed_time":11.03986157,"remaining_time":1.091854441},
{"learn":[0.5795969153],"iteration":273,"passed_time":11.08396926,"remaining_time":1.051763507},
{"learn":[0.5795467233],"iteration":274,"passed_time":11.12075841,"remaining_time":1.010978037},
{"learn":[0.5794296364],"iteration":275,"passed_time":11.16482159,"remaining_time":0.9708540511},
{"learn":[0.5793752931],"iteration":276,"passed_time":11.20381099,"remaining_time":0.9302803351},
{"learn":[0.5793197946],"iteration":277,"passed_time":11.24550937,"remaining_time":0.8899323965},
{"learn":[0.5792639082],"iteration":278,"passed_time":11.28205154,"remaining_time":0.849186675},
{"learn":[0.5792146236],"iteration":279,"passed_time":11.32210049,"remaining_time":0.8087214633},
{"learn":[0.5791456037],"iteration":280,"passed_time":11.36857932,"remaining_time":0.7686939752},
{"learn":[0.5790953727],"iteration":281,"passed_time":11.41753774,"remaining_time":0.7287790044},
{"learn":[0.5790446923],"iteration":282,"passed_time":11.46394148,"remaining_time":0.6886466611},
{"learn":[0.5789922395],"iteration":283,"passed_time":11.50784681,"remaining_time":0.6483293978},
{"learn":[0.5789430737],"iteration":284,"passed_time":11.54966444,"remaining_time":0.6078770758},
{"learn":[0.5788562595],"iteration":285,"passed_time":11.59339698,"remaining_time":0.5675089431},
{"learn":[0.578800522],"iteration":286,"passed_time":11.63310124,"remaining_time":0.5269348994},
{"learn":[0.578754638],"iteration":287,"passed_time":11.67524848,"remaining_time":0.4864686867},
{"learn":[0.5786819089],"iteration":288,"passed_time":11.7130069,"remaining_time":0.4458237919},
{"learn":[0.5786290773],"iteration":289,"passed_time":11.75592935,"remaining_time":0.4053768742},
{"learn":[0.5785383981],"iteration":290,"passed_time":11.79551055,"remaining_time":0.3648096047},
{"learn":[0.5784763148],"iteration":291,"passed_time":11.8408364,"remaining_time":0.3244064766},
{"learn":[0.5783969442],"iteration":292,"passed_time":11.88785988,"remaining_time":0.2840103042},
{"learn":[0.5782905741],"iteration":293,"passed_time":11.93196207,"remaining_time":0.24350943},
{"learn":[0.5782330011],"iteration":294,"passed_time":11.97210581,"remaining_time":0.2029170477},
{"learn":[0.5781647394],"iteration":295,"passed_time":12.00709885,"remaining_time":0.1622580926},
{"learn":[0.5781190216],"iteration":296,"passed_time":12.04188145,"remaining_time":0.1216351662},
{"learn":[0.5780639657],"iteration":297,"passed_time":12.07949259,"remaining_time":0.08107042008},
{"learn":[0.5780185734],"iteration":298,"passed_time":12.12130623,"remaining_time":0.04053948572},
{"learn":[0.577970465],"iteration":299,"passed_time":12.15673319,"remaining_time":0}
]}